ge/Classifiers.py
ge/__init__.py
ge/biasedRandomWalk.py
ge/deepWalk.py
ge/main_ge.py
ge/main_trainClf.py
ge/node2vec.py
ge/randomWalkEmbedding.py
ge/skipgram.py
ge/struc2vec.py
ge/utils.py
dgllge-1.0.3.dist-info/LICENSE.txt
dgllge-1.0.3.dist-info/METADATA
dgllge-1.0.3.dist-info/WHEEL
dgllge-1.0.3.dist-info/entry_points.txt
dgllge-1.0.3.dist-info/top_level.txt
dgllge-1.0.3.dist-info/RECORD
