Metadata-Version: 2.1
Name: dgllge
Version: 1.0.3
Summary: Graph Embedding Models
Home-page: https://github.com/sahibzada-irfanullah/Graph-Embedding
Author: Irfan Ullah
Author-email: Irfan Ullah <irfan@khu.ac.kr>
Project-URL: Homepage, https://github.com/sahibzada-irfanullah
Project-URL: repository, https://github.com/sahibzada-irfanullah/Graph-Embedding
Project-URL: documentation, https://github.com/sahibzada-irfanullah/Graph-Embedding/blob/main/README.md
Keywords: graph embedding,embedding,ge
Classifier: License :: OSI Approved :: MIT License
Classifier: Programming Language :: Python :: 3.7
Requires-Python: >=3.7
License-File: LICENSE.txt
Requires-Dist: fastdtw (>=0.3.4)
Requires-Dist: gensim (>=4.2.0)
Requires-Dist: matplotlib (>=3.5.2)
Requires-Dist: networkx (>=2.6.3)
Requires-Dist: numpy (>=1.21.6)
Requires-Dist: pandas (>=1.3.5)
Requires-Dist: scikit-learn (>=1.0.2)
Requires-Dist: scipy (>=1.7.3)
Requires-Dist: torch (>=1.11.0)
Requires-Dist: torchvision (>=0.12.0)
